{
  "id": "23c4a632664894f75f14051181727408",
  "title": "Is Airplane Mode on Flights Necessary or Outdated? (2025)",
  "content": "If you don’t, your flight won’t crash, but ignoring airplane mode uses up your battery and annoys the pilot.",
  "date": "Sat, 12 Apr 2025 12:02:00 +0000",
  "link": "https://www.wired.com/story/phone-on-airplane-mode-how-to/",
  "source": "https://www.wired.com/feed/rss",
  "categories": [
    "Gear",
    "Gear / How To and Advice",
    "Travel",
    "Aviation",
    "phones",
    "how-to",
    "smartphones",
    "Airplanes",
    "Rough Landing"
  ],
  "fetch_timestamp": "2025-04-14T23:33:31.248919",
  "processed": false
}